pysqlcrypt/__init__.py
pysqlcrypt/crypto.py
pysqlcrypt/py.typed
pysqlcrypt-0.2.0.dist-info/METADATA
pysqlcrypt-0.2.0.dist-info/WHEEL
pysqlcrypt-0.2.0.dist-info/licenses/LICENSE
pysqlcrypt-0.2.0.dist-info/RECORD
