Metadata-Version: 2.4
Name: pysqlcrypt
Version: 0.2.0
Summary: Python implementation of SQL Server's ENCRYPTBYPASSPHRASE and DECRYPTBYPASSPHRASE
Project-URL: Homepage, https://github.com/ivan-loh/pysqlcrypt
Project-URL: Documentation, https://github.com/ivan-loh/pysqlcrypt#readme
Project-URL: Repository, https://github.com/ivan-loh/pysqlcrypt
Project-URL: Issues, https://github.com/ivan-loh/pysqlcrypt/issues
Author-email: Ivan <warm.tiger5970@fastmail.com>
License-Expression: MIT
License-File: LICENSE
Keywords: 3des,aes,decryptbypassphrase,decryption,encryptbypassphrase,encryption,mssql,sql-server
Classifier: Development Status :: 4 - Beta
Classifier: Intended Audience :: Developers
Classifier: License :: OSI Approved :: MIT License
Classifier: Operating System :: OS Independent
Classifier: Programming Language :: Python :: 3
Classifier: Programming Language :: Python :: 3.9
Classifier: Programming Language :: Python :: 3.10
Classifier: Programming Language :: Python :: 3.11
Classifier: Programming Language :: Python :: 3.12
Classifier: Programming Language :: Python :: 3.13
Classifier: Topic :: Database
Classifier: Topic :: Security :: Cryptography
Classifier: Typing :: Typed
Requires-Python: >=3.9
Requires-Dist: pycryptodome>=3.19.0
Provides-Extra: dev
Requires-Dist: mypy>=1.0.0; extra == 'dev'
Requires-Dist: pytest-cov>=4.0.0; extra == 'dev'
Requires-Dist: pytest>=7.0.0; extra == 'dev'
Requires-Dist: ruff>=0.1.0; extra == 'dev'
